letpn_bda/__init__.py
letpn_bda/db/week1.json
letpn_bda/db/week10.json
letpn_bda/db/week11.json
letpn_bda/db/week12.json
letpn_bda/db/week2.json
letpn_bda/db/week3.json
letpn_bda/db/week4.json
letpn_bda/db/week5.json
letpn_bda/db/week6.json
letpn_bda/db/week7.json
letpn_bda/db/week8.json
letpn_bda/db/week9.json
letpn_bda/main.py
letpn_bda/quiz_data.json
letpn_bda/quiz_func.py
letpn_bda/raw_text/week1.txt
letpn_bda/raw_text/week10.txt
letpn_bda/raw_text/week11.txt
letpn_bda/raw_text/week12.txt
letpn_bda/raw_text/week2.txt
letpn_bda/raw_text/week3.txt
letpn_bda/raw_text/week4.txt
letpn_bda/raw_text/week5.txt
letpn_bda/raw_text/week6.txt
letpn_bda/raw_text/week7.txt
letpn_bda/raw_text/week8.txt
letpn_bda/raw_text/week9.txt
letpn_bda-1.0.0.dist-info/entry_points.txt
letpn_bda-1.0.0.dist-info/WHEEL
letpn_bda-1.0.0.dist-info/METADATA
letpn_bda-1.0.0.dist-info/RECORD
