Metadata-Version: 2.1
Name: letpn-bda
Version: 1.0.0
Summary: This is a Simple Quiz app for Practicing
Author: PRITAM CHAKRABORTY
Author-email: pritam.chk98@gmail.com
Requires-Python: >=3.10,<4.0
Classifier: Programming Language :: Python :: 3
Classifier: Programming Language :: Python :: 3.10
Requires-Dist: typer[all] (>=0.4.1,<0.5.0)
